[
  {
    "time_start": "2025-12-17T00:00:00",
    "SEK_per_kWh": 0.24377
  },
  {
    "time_start": "2025-12-17T01:00:00",
    "SEK_per_kWh": 0.22825
  },
  {
    "time_start": "2025-12-17T02:00:00",
    "SEK_per_kWh": 0.22072
  },
  {
    "time_start": "2025-12-17T03:00:00",
    "SEK_per_kWh": 0.22521
  },
  {
    "time_start": "2025-12-17T04:00:00",
    "SEK_per_kWh": 0.23829
  },
  {
    "time_start": "2025-12-17T05:00:00",
    "SEK_per_kWh": 0.2725
  },
  {
    "time_start": "2025-12-17T06:00:00",
    "SEK_per_kWh": 0.33151
  },
  {
    "time_start": "2025-12-17T07:00:00",
    "SEK_per_kWh": 0.39081
  },
  {
    "time_start": "2025-12-17T08:00:00",
    "SEK_per_kWh": 0.4057
  },
  {
    "time_start": "2025-12-17T09:00:00",
    "SEK_per_kWh": 0.38454
  },
  {
    "time_start": "2025-12-17T10:00:00",
    "SEK_per_kWh": 0.35608
  },
  {
    "time_start": "2025-12-17T11:00:00",
    "SEK_per_kWh": 0.29524
  },
  {
    "time_start": "2025-12-17T12:00:00",
    "SEK_per_kWh": 0.28356
  },
  {
    "time_start": "2025-12-17T13:00:00",
    "SEK_per_kWh": 0.27258
  },
  {
    "time_start": "2025-12-17T14:00:00",
    "SEK_per_kWh": 0.27253
  },
  {
    "time_start": "2025-12-17T15:00:00",
    "SEK_per_kWh": 0.28682
  },
  {
    "time_start": "2025-12-17T16:00:00",
    "SEK_per_kWh": 0.28698
  },
  {
    "time_start": "2025-12-17T17:00:00",
    "SEK_per_kWh": 0.28673
  },
  {
    "time_start": "2025-12-17T18:00:00",
    "SEK_per_kWh": 0.27091
  },
  {
    "time_start": "2025-12-17T19:00:00",
    "SEK_per_kWh": 0.2557
  },
  {
    "time_start": "2025-12-17T20:00:00",
    "SEK_per_kWh": 0.22357
  },
  {
    "time_start": "2025-12-17T21:00:00",
    "SEK_per_kWh": 0.21607
  },
  {
    "time_start": "2025-12-17T22:00:00",
    "SEK_per_kWh": 0.20104
  },
  {
    "time_start": "2025-12-17T23:00:00",
    "SEK_per_kWh": 0.18192
  }
]